{
  "products": [
    {
      "title": "roba Gigoteuse Organic \u00ab\u00a0Lil Planet\u00a0\u00bb, en trois tailles",
      "price": "26.99\u20ac",
      "description": "Gigoteuse roba Organic \u00ab\u00a0Lil Planet\u00a0\u00bbLa gigoteuse roba organic \u00ab\u00a0Lil Planet\u00a0\u00bb garantit une sensation de douceur et de sec dans le lit de b\u00e9b\u00e9 gr\u00e2ce \u00e0 son tissu en mousseline 100 % coton bio, non toxique et absorbant. La gigoteuse pour b\u00e9b\u00e9s et enfants est fabriqu\u00e9e exclusivement \u00e0 partir de mat\u00e9riaux respirants afin d\u2019\u00e9viter la surchauffe de votre b\u00e9b\u00e9, en particulier en \u00e9t\u00e9. La gigoteuse bio est fabriqu\u00e9e \u00e0 partir de coton pur, durable et non trait\u00e9. M\u00eame apr\u00e8s de nombreux lavages, les gigoteuses pour b\u00e9b\u00e9s conservent leur forme et leur beau toucher. Gr\u00e2ce \u00e0 un traitement de surface sp\u00e9cial et \u00e0 un pr\u00e9lavage, les gigoteuses restent super douces. La gamme textile roba Organic \u00ab\u00a0Lil Planet\u00a0\u00bb est disponible dans les couleurs tendance rose/ mauve, bleu clair/bleu ciel, gris argent\u00e9 et vert frosty. Les gigoteuses sont fabriqu\u00e9es de mani\u00e8re durable selon le Global Organic Textile Standard GOTS et dans des conditions sociales et \u00e9quitables selon la Business Social Compliance Initiative (BSCI). Toutes les gigoteuses pour b\u00e9b\u00e9s et enfants sont certifi\u00e9es Oeko-Tex\u00ae Standard 100 selon les crit\u00e8res \u00e9cologiques les plus stricts. La gigoteuse est lavable \u00e0 40\u00a0\u00b0C, une temp\u00e9rature respectueuse de l\u2019environnement.Caract\u00e9ristiquesGigoteuse d\u2019une longueur de 70, 90 ou 110 cmRev\u00eatement en mousselineLa longueur 70 correspond \u00e0 la taille 62/68La longueur 90 correspond \u00e0 la taille 86/92La longueur 110 correspond \u00e0 la taille 104/110\u00c2ge : d\u00e8s la naissanceMat\u00e9riauHousse\u00a0: 100\u00a0% cotonDoublure int\u00e9rieure : 100 % cotonRemplissage : 100 % polyester non tiss\u00e9DimensionsEnv. l 45 x L 70 cmEnv. l 50 x L 90 cmEnv. l 65 x L 110 cmPoidsenv. l 45 x L 70 cm\u00a0: 400 genv. l 50 x L 90 cm\u00a0: 600 genv. l 65 x L 110 cm\u00a0: 700 g",
      "images": [
        "https://www.lidl.fr/assets/80b9eb6474d3fd4cdfe82b63d74bae13.jpeg",
        "https://www.lidl.fr/assets/9be1e04ef7101818c63c403d52e50d28.jpeg",
        "https://www.lidl.fr/assets/6167535a800e312f7e002f3db5c4dd40.jpeg",
        "https://www.lidl.fr/assets/47c1c4897e8bc60efac2ecbc4bc34e02.jpeg",
        "https://www.lidl.fr/assets/2761172ba33f78fbf57572355cdf0ae4.jpeg",
        "https://www.lidl.fr/assets/05ec8592facbd7410d447451f8653dcf.jpeg",
        "https://www.lidl.fr/assets/ca6b005d8cf5cd8169f31ab5c1caf83f.jpeg",
        "https://www.lidl.fr/assets/b639e01913a0f7530656869f9f6b6be7.jpeg",
        "https://www.lidl.fr/assets/4368f93ef3a58ca6464bd1f64af96808.jpeg",
        "https://www.lidl.fr/assets/5f3b16505bd057586744226d821888c6.jpeg",
        "https://www.lidl.fr/assets/47871a32de251653bd909835e87ecea5.jpeg",
        "https://www.lidl.fr/assets/5f14b34ba1002d7589b1a96a29e1c382.jpeg",
        "https://www.lidl.fr/assets/feeee04e62484a569bbf045328960369.jpeg",
        "https://www.lidl.fr/assets/fda8512a381c9771a6f3a90d78b252af.jpeg",
        "https://www.lidl.fr/assets/d73d5e7c2867a39e4e902a5e5cc701d7.jpeg",
        "https://www.lidl.fr/assets/d2c934c14d02e184fa293c0a42ebc7e9.jpeg",
        "https://www.lidl.fr/assets/bdc62d10630242f4eb7ca7c56ab32293.jpeg",
        "https://www.lidl.fr/assets/2b5affd3308f8d81ece90a1b955fce7f.jpeg",
        "https://www.lidl.fr/assets/f120e8431f66d127cc581b31bac18be3.jpeg",
        "https://www.lidl.fr/assets/1e1b4452909334377bc7f7cad6f326d9.jpeg",
        "https://www.lidl.fr/assets/e9fca7aa56d1c2e7773774516d992fe1.jpeg",
        "https://www.lidl.fr/assets/554b0fb6094f14e0890a15563516ebc4.jpeg",
        "https://www.lidl.fr/assets/1d4d5d63409989cf9f04d3d60985baf5.jpeg",
        "https://www.lidl.fr/assets/e27d328f5ae9bfee267bdf3b57988112.jpeg",
        "https://www.lidl.fr/assets/e5d1188fe97ddea97c6df3efc29ef5e0.jpeg",
        "https://www.lidl.fr/assets/d332045fcd9ac7393b33b237a0218dd2.jpeg",
        "https://www.lidl.fr/assets/c8087ff4ffb150db52ba798f64a9d8b8.jpeg",
        "https://www.lidl.fr/assets/ae17ef5fd364c1404f00d7a069dbe70e.jpeg",
        "https://www.lidl.fr/assets/b20b4441765e39c95c5663188abae1bb.jpeg",
        "https://www.lidl.fr/assets/af46fe106c340c8f91b2b84103641280.jpeg",
        "https://www.lidl.fr/assets/1db0d80339588b753f5ef5b01a799935.jpeg",
        "https://www.lidl.fr/assets/bf745a467f24934703c1dcbaf749070e.jpeg",
        "https://www.lidl.fr/assets/82b8a4f905df0276be5d6ec4d860ff4d.jpeg",
        "https://www.lidl.fr/assets/13bcaeaf21dc2a3cbf7c01a0f7b1b45f.jpeg",
        "https://www.lidl.fr/assets/9f3ecffe5239b4028d19af0f5d132014.jpeg"
      ]
    },
    {
      "title": "TR\u00c4UMELAND, Gigoteuse d'\u00e9t\u00e9 \u00ab\u00a0Aime-moi\u00a0\u00bb, en mousseline de coton, TOG 0,5",
      "price": "32.99\u20ac",
      "description": "TR\u00c4UMELAND, Gigoteuse d'\u00e9t\u00e9 \u00ab Aime-moi \u00bb, en mousseline de coton, TOG 0,5Caract\u00e9ristiquesFente d'a\u00e9ration \u00e0 l'extr\u00e9mit\u00e9 du pied permettant un apport d'air optimal selon les besoinsParfait pour les chaudes nuits d'\u00e9t\u00e9Fermeture \u00e9clair de s\u00e9curit\u00e9 centraleSans azurants optiquesGarantie de tests multiples et ind\u00e9pendants sur les substances nocives\u00a0: d\u00e9montr\u00e9 comme \u00e9tant appropri\u00e9 pour une utilisation dans le lit de b\u00e9b\u00e9Mati\u00e8re100\u00a0% mousseline de cotonTailles60 - 110",
      "images": [
        "https://www.lidl.fr/assets/gcp8aa506adc9ba42a6946c538ab21e1da2.jpeg",
        "https://www.lidl.fr/assets/gcp427b8a48e2c34dc4b46d096f8ff894c1.jpeg",
        "https://www.lidl.fr/assets/gcp8f21c896e6904d99a5357f411a60fe76.jpeg",
        "https://www.lidl.fr/assets/gcp07991e901fd84c7ca81b2e404df33496.jpeg"
      ]
    },
    {
      "title": "TR\u00c4UMELAND, Coussin d'allaitement",
      "price": "67.99\u20ac",
      "description": "TR\u00c4UMELAND, Coussin d'allaitementCaract\u00e9ristiquesOffre une grossesse agr\u00e9able et une relaxation pendant l'allaitementAjustement optimal aux contours du corps tout en offrant un soutien - avec de nombreuses possibilit\u00e9s d'utilisation\u00a0:Pendant la grossesse\u00a0: il offre un soutien en position assise ou couch\u00e9e et assure un sommeil d\u00e9tendu. Gr\u00e2ce \u00e0 son remplissage en micro-perles EPS silencieuses, le coussin d'allaitement s'adapte parfaitement \u00e0 la forme du corps et donc au ventre croissant.Pendant l'allaitement\u00a0: une fois que le b\u00e9b\u00e9 est n\u00e9, le coussin permet \u00e0 la m\u00e8re d'avoir au moins une main libre pendant l'allaitement. De plus, les bras, les \u00e9paules, la nuque et les muscles du dos de la m\u00e8re sont soulag\u00e9s, car le poids du b\u00e9b\u00e9 repose sur le coussin pendant l'allaitement.Pendant la phase de la petite enfance\u00a0: le coussin d'allaitement peut \u00eatre utilis\u00e9 de mani\u00e8re id\u00e9ale comme coussin de soutien et de positionnement pour les petits.Housse amovible et lavable \u00e0 60\u00a0\u00b0C\u00a0; rembourrage lavable \u00e0 40\u00a0\u00b0CMati\u00e8resHousse\u00a0: 100\u00a0% cotonRemplissage\u00a0: fines billes EPS silencieusesDimensionsEnviron l 21 x H 25 x P 190 cmPoidsenviron 1.39 kg",
      "images": [
        "https://www.lidl.fr/assets/9ed5a75c64d89baa2e6da8c3b3a33d74.jpeg",
        "https://www.lidl.fr/assets/7070714085144c4ea8b92b83acb81a82.jpeg",
        "https://www.lidl.fr/assets/90ff9826a164c97c27035b49112764d5.jpeg",
        "https://www.lidl.fr/assets/54dc0bb460b16a670e55b0feaab7804b.jpeg",
        "https://www.lidl.fr/assets/c8d5c73d6d3cf4c0441ba3ba6525d0e9.jpeg"
      ]
    },
    {
      "title": "Reer Tapis de protection pour si\u00e8ge arri\u00e8re de la voiture \u00bbTravelKid MaxiProtect\u00bb, tapis antid\u00e9rapant",
      "price": "16.99\u20ac",
      "description": "Caract\u00e9ristiquesSurface extra large, id\u00e9ale pour les si\u00e8ges reboardersTapis antid\u00e9rapant pour un maintien s\u00fbr du si\u00e8ge d\u2019enfantProt\u00e8ge des points de pression et de la salet\u00e9 dans la voitureCompatible avec ISOFIXFacile \u00e0 nettoyer gr\u00e2ce \u00e0 une mati\u00e8re hydrofuge et antisalissanteDes poches pratiques permettent de mettre de l\u2019ordreConvient \u00e0 tous les si\u00e8ges de voiture traditionnels\u00c2ge recommand\u00e9\u00a0: d\u00e8s la naissanceMati\u00e8re80\u00a0% polyester, 20\u00a0% polyur\u00e9thaneDimensionsenv. 46\u00a0x\u00a0120 cmPoidsenv. 620 gContenu de la livraison1 tapis de protection pour si\u00e8ge de voiture",
      "images": [
        "https://www.lidl.fr/assets/9e5035eb6e368fc393eaa36cc97b4872.jpeg",
        "https://www.lidl.fr/assets/5ab3633db98cb0da37e56d8e0a1cb37e.jpeg",
        "https://www.lidl.fr/assets/6bec1d66bded7ef94333752ff02d5408.jpeg",
        "https://www.lidl.fr/assets/1051ea19c881678ffca859848d1d8ce0.jpeg",
        "https://www.lidl.fr/assets/86e308ec47b58661d600bddff517e478.jpeg",
        "https://www.lidl.fr/assets/755a728079365fa45d9d4c261aaff806.jpeg",
        "https://www.lidl.fr/assets/6fe4940e783ac4dd858b29b8acafc713.jpeg",
        "https://www.lidl.fr/assets/17e8cef59d3236335e4fff16de09f45c.jpeg",
        "https://www.lidl.fr/assets/d46db1c41566ad0fda2df372a6baedc0.jpeg",
        "https://www.lidl.fr/assets/cf3e141123f65d3358255d1aad452147.jpeg"
      ]
    },
    {
      "title": "TR\u00c4UMELAND, Gigoteuse d'\u00e9t\u00e9 \u00ab\u00a0Aime moi\u00a0\u00bb, en mousseline de coton, TOG 0,5",
      "price": "35.99\u20ac",
      "description": "TR\u00c4UMELAND, Gigoteuse d'\u00e9t\u00e9 \u00ab Aime moi \u00bb, en mousseline de coton, TOG 0,5Caract\u00e9ristiquesFente d'a\u00e9ration \u00e0 l'extr\u00e9mit\u00e9 du pied permettant un apport d'air optimal selon les besoinsParfait pour les chaudes nuits d'\u00e9t\u00e9Fermeture \u00e9clair de s\u00e9curit\u00e9 centraleSans azurants optiquesGarantie de tests multiples et ind\u00e9pendants sur les substances nocives\u00a0: d\u00e9montr\u00e9 comme \u00e9tant appropri\u00e9 pour une utilisation dans le lit de b\u00e9b\u00e9TOG : 0,5Couleur :abricotMati\u00e8re100\u00a0% mousseline de cotonTailles60 - 110Age3 mois au 4/5 ans",
      "images": [
        "https://www.lidl.fr/assets/gcpa962cc3643144b7e8786eb7c26b74ee7.jpeg",
        "https://www.lidl.fr/assets/gcpd06a9a6a331041d487cecae8bbc7721e.jpeg",
        "https://www.lidl.fr/assets/gcp0d26ceb938354207b03c5b3967f36a70.jpeg",
        "https://www.lidl.fr/assets/gcp5b14f90160ae459b998dfbb0a2060abf.jpeg"
      ]
    },
    {
      "title": "Badabulle Tapis de bain",
      "price": "15.99\u20ac",
      "description": "Badabulle Tapis de bainDouble avantage : le tapis de bain Badabulle d\u00e9cor\u00e9 de motifs marins chics sert de protection antid\u00e9rapante et d\u2019indicateur de temp\u00e9rature. Pas moins de 82 ventouses sous le tapis de bain assurent un maintien optimal et une protection fiable contre les glissades dans la baignoire ou la douche.Il suffit de regarder le tapis de bain pour voir si l\u2019eau du bain est \u00e0 la bonne temp\u00e9rature. Un indicateur de chaleur indique le degr\u00e9 correspondant en fonction de la couleur.Accompagnez votre petit dans ses aventures avec les adorables poissons, pieuvres et baleines et faites de votre bain quotidien un moment de plaisir\u00a0!D\u00e9couvrez \u00e9galement nos autres produits de la collection Badabulle Rats d\u2019eau pour encore plus de plaisir dans le bain.Pourquoi vous et votre petit rat d\u2019eau allez adorer le tapis de bain avec indicateur de temp\u00e9rature :Antid\u00e9rapant avec 82 ventouses pour un maintien optimal et s\u00fbrIndicateur de temp\u00e9rature : indicateur sensible \u00e0 la chaleur pour plus de s\u00e9curit\u00e9Facile \u00e0 nettoyerProtection anti moisissuresConvient pour baignoire ou doucheMat\u00e9riau100 % PVCDimensions (LxlxH)environ 40 x 70 x 2 cmPoidsenviron 410 g",
      "images": [
        "https://www.lidl.fr/assets/gcp46a4c12439d943508fa732efc99786ef.jpeg",
        "https://www.lidl.fr/assets/gcp167ccd1062a345648db052c1b3998c45.jpeg",
        "https://www.lidl.fr/assets/gcp45fe7e0521ce490b99dba8a985d870d9.jpeg",
        "https://www.lidl.fr/assets/gcp71aff8222291445394f164fc6fdf0769.jpeg",
        "https://www.lidl.fr/assets/gcp3b1a886b353348e98c9d136248ead2b8.jpeg"
      ]
    },
    {
      "title": "Fillikid Chanceli\u00e8re d'hiver pour cosy",
      "price": "24.99\u20ac",
      "description": "Fillikid Chanceli\u00e8re d'hiver pour cosyLa chanceli\u00e8re d'hiver Cozy Big est le mod\u00e8le d'entr\u00e9e de gamme de Fillikid pour les chanceli\u00e8res de poussette, de running et de landau. Malgr\u00e9 son prix tr\u00e8s attractif, elle r\u00e9pond aux exigences \u00e9lev\u00e9es de Fillikid en mati\u00e8re de qualit\u00e9 et de finition et est une chanceli\u00e8re d'hiver \u00e0 part enti\u00e8re. Elle est doubl\u00e9e d'une polaire douce et moelleuse dans laquelle votre prog\u00e9niture se sentira en s\u00e9curit\u00e9. La Cozy Big convainc \u00e9galement par ses dimensions (50 x 100 cm) et son faible poids. Sa fermeture \u00e9clair sur toute la longueur \u00e0 l'avant facilite l'acc\u00e8s. De plus, la partie pour les pieds peut \u00eatre ouverte de mani\u00e8re pratique gr\u00e2ce \u00e0 une fermeture \u00e0 glissi\u00e8re.Caract\u00e9ristiquesMat\u00e9riau ext\u00e9rieur coupe-vent et d\u00e9perlantDoubl\u00e9e d'un polaire doux et moelleuxFermeture \u00e0 glissi\u00e8re sur toute la longueur du devantConvient aux buggies, aux poussettes et aux landausAvec fentes pour ceinture et ouverture pour les piedsConvient pour un lavage en machine \u00e0 30 degr\u00e9sFaible poids propreRecommandation d'\u00e2ge : \u00e0 partir de 6 moisCompositionExt\u00e9rieur : 100 % polyesterInt\u00e9rieur : 100 % polaire corailDimensionsEnviron L 100 x l 50 x H 10 cmPoidsEnviron\u00a0610 g",
      "images": [
        "https://www.lidl.fr/assets/gcpfdb1d72d999041f4b092b128bcf7a805.jpeg",
        "https://www.lidl.fr/assets/gcp1948bdd16d604a93b7ec7ed9f4cd1580.jpeg",
        "https://www.lidl.fr/assets/gcp76ad39c54e594d8dbd8e5da5ff01983a.jpeg",
        "https://www.lidl.fr/assets/gcpcdcb608f3c094ebc9c6791a4f1cc4034.jpeg",
        "https://www.lidl.fr/assets/gcpd921f469f201442c97823176d0d17df7.jpeg",
        "https://www.lidl.fr/assets/gcp05356053973243a7a22981dfba2e1911.jpeg",
        "https://www.lidl.fr/assets/gcp6c013b390f2648c497fd2b09242e55c8.jpeg",
        "https://www.lidl.fr/assets/gcpe25d41ecaa014f129f99d484b2b4e9ba.jpeg",
        "https://www.lidl.fr/assets/gcp81fa1237fb3443d3bf6672775792235b.jpeg",
        "https://www.lidl.fr/assets/gcp16219673781941b79329e9872f1b2e4b.jpeg",
        "https://www.lidl.fr/assets/gcp99c8472d9dea41809b1958bec832fb46.jpeg",
        "https://www.lidl.fr/assets/gcp81c6ccb618fb4ae2acbe5bfcf86aa877.jpeg",
        "https://www.lidl.fr/assets/gcpb0daa58557ba4943add140b2387594b3.jpeg",
        "https://www.lidl.fr/assets/gcpe7206a7896dc403295b2b566de2ef187.jpeg",
        "https://www.lidl.fr/assets/gcp2bee5900dfe34cd29aca7b4519e26fe7.jpeg",
        "https://www.lidl.fr/assets/gcp790860e76fc44ce1bffe84753dbdf9cb.jpeg",
        "https://www.lidl.fr/assets/gcp07a42e8fbba34cf0a4cc208e1ff330c9.jpeg",
        "https://www.lidl.fr/assets/gcp2476c385a08742058f758a5e21465074.jpeg"
      ]
    }
  ]
}